{
  "0": [
    "p"
  ],
  "1": [
    "a"
  ],
  "2": [
    "t"
  ],
  "3": [
    "h"
  ],
  "4": [
    "o"
  ],
  "5": [
    "l"
  ],
  "6": [
    "o"
  ],
  "7": [
    "g"
  ],
  "8": [
    "i"
  ],
  "9": [
    "c"
  ],
  "10": [
    "o"
  ],
  "11": [
    "p"
  ],
  "12": [
    "s"
  ],
  "13": [
    "y"
  ],
  "14": [
    "c"
  ],
  "15": [
    "h"
  ],
  "16": [
    "o"
  ],
  "17": [
    "l"
  ],
  "18": [
    "o"
  ],
  "19": [
    "g"
  ],
  "20": [
    "i"
  ],
  "21": [
    "c"
  ],
  "22": [
    "a"
  ],
  "23": [
    "l"
  ]
}